[{"modulars":[{"lists":["5b343be9a818381dfc985dd6","5b343be9a818381dfc985dd7"],"date_start":"2018-03-25T00:00:00.000Z","date_end":"2018-04-25T00:00:00.000Z","facilitators":"5b343be9a818381dfc985db8","modules":"5b343be9a818381dfc985dc6","_id":"5b343be9a818381dfc985dd4"}],"inscriptions":[{"_id":"5b343be9a818381dfc985de2","total_price":600,"module_price":150,"bolivianos_price":3,"dolares_price":300,"canceled_price":300,"price_event":2000,"receipt":"4567","ci":"1234567","cellphone":76543218,"persons":"5b343be9a818381dfc985dd0","users":"5b343be9a818381dfc985db5"},{"_id":"5b343be9a818381dfc985de1","total_price":600,"module_price":150,"bolivianos_price":0,"dolares_price":300,"canceled_price":300,"price_event":1400,"receipt":"4568","ci":"1234566","cellphone":79452311,"persons":"5b343be9a818381dfc985dd1","users":"5b343be9a818381dfc985db6"},{"_id":"5b343be9a818381dfc985de0","total_price":600,"module_price":150,"bolivianos_price":300,"dolares_price":0,"canceled_price":300,"price_event":2000,"receipt":"4569","ci":"712337757","cellphone":60121234,"persons":"5b343be9a818381dfc985dd2","users":"5b343be9a818381dfc985db5"}],"record_date":"2018-06-28T01:37:45.921Z","_id":"5b343be9a818381dfc985dd5","name":"seguridad imformatica y redes sociales","description":"solo para ejecutivos","date_start":"2018-06-25T00:00:00.000Z","total":30,"programs":"5b343be9a818381dfc985dc4","offices":"5b343be9a818381dfc985daf","date_end":null,"active":true,"__v":0}]